{
    "Ar36": {
        "error": 9.853717248469463e-09,
        "error_type": "",
        "fit": "previous",
        "references": [
            {
                "exclude": false,
                "record_id": "ba-01-n-17243"
            }
        ],
        "value": 3.3834399128265333e-07
    },
    "Ar37": {
        "error": 2.932927312295082e-07,
        "error_type": "",
        "fit": "previous",
        "references": [
            {
                "exclude": false,
                "record_id": "ba-01-n-17243"
            }
        ],
        "value": 3.971316716399031e-07
    },
    "Ar38": {
        "error": 3.4889347269213e-07,
        "error_type": "",
        "fit": "previous",
        "references": [
            {
                "exclude": false,
                "record_id": "ba-01-n-17243"
            }
        ],
        "value": 1.8526185349265062e-09
    },
    "Ar39": {
        "error": 2.7325405230513766e-07,
        "error_type": "",
        "fit": "previous",
        "references": [
            {
                "exclude": false,
                "record_id": "ba-01-n-17243"
            }
        ],
        "value": 2.7076180128494595e-07
    },
    "Ar40": {
        "error": 7.941683142207154e-07,
        "error_type": "",
        "fit": "previous",
        "references": [
            {
                "exclude": false,
                "record_id": "ba-01-n-17243"
            }
        ],
        "value": 6.067707523533164e-05
    }
}