{
    "Ar36": {
        "error": 8.548731851320009e-09,
        "error_type": "",
        "fit": "previous",
        "references": [
            {
                "exclude": false,
                "record_id": "ba-01-n-17214"
            }
        ],
        "value": 3.1477112434009046e-07
    },
    "Ar37": {
        "error": 3.1180579692452167e-07,
        "error_type": "",
        "fit": "previous",
        "references": [
            {
                "exclude": false,
                "record_id": "ba-01-n-17214"
            }
        ],
        "value": 8.165490715479435e-07
    },
    "Ar38": {
        "error": 2.0974627869151993e-07,
        "error_type": "",
        "fit": "previous",
        "references": [
            {
                "exclude": false,
                "record_id": "ba-01-n-17214"
            }
        ],
        "value": 1.949604487986906e-08
    },
    "Ar39": {
        "error": 3.6153042397220926e-07,
        "error_type": "",
        "fit": "previous",
        "references": [
            {
                "exclude": false,
                "record_id": "ba-01-n-17214"
            }
        ],
        "value": -3.7610950265136965e-08
    },
    "Ar40": {
        "error": 1.5647814544154725e-06,
        "error_type": "",
        "fit": "previous",
        "references": [
            {
                "exclude": false,
                "record_id": "ba-01-n-17214"
            }
        ],
        "value": 6.141625343947509e-05
    }
}